kivyIsoDatepicker/__init__.py
kivyIsoDatepicker/datepicker.py
kivyIsoDatepicker-1.0.2.dist-info/LICENSE
kivyIsoDatepicker-1.0.2.dist-info/METADATA
kivyIsoDatepicker-1.0.2.dist-info/WHEEL
kivyIsoDatepicker-1.0.2.dist-info/top_level.txt
kivyIsoDatepicker-1.0.2.dist-info/RECORD
